.gitignore
bootstrap.py
buildout.cfg
setup.cfg
setup.py
docs/HISTORY.txt
docs/INSTALL.txt
docs/LICENSE.GPL
docs/LICENSE.txt
transmogrify/__init__.py
transmogrify.htmltesting.egg-info/PKG-INFO
transmogrify.htmltesting.egg-info/SOURCES.txt
transmogrify.htmltesting.egg-info/dependency_links.txt
transmogrify.htmltesting.egg-info/entry_points.txt
transmogrify.htmltesting.egg-info/namespace_packages.txt
transmogrify.htmltesting.egg-info/not-zip-safe
transmogrify.htmltesting.egg-info/requires.txt
transmogrify.htmltesting.egg-info/top_level.txt
transmogrify/htmltesting/__init__.py
transmogrify/htmltesting/configure.zcml
transmogrify/htmltesting/debugsection.py
transmogrify/htmltesting/htmlsource.py
transmogrify/htmltesting/runner.py
transmogrify/htmltesting/sectionfeedback.py
transmogrify/htmltesting/sections.zcml
transmogrify/htmltesting/tests.py
transmogrify/htmltesting/testsites.txt
transmogrify/htmltesting/test_staticsite/cia-plone-view-source.jpg
transmogrify/htmltesting/test_staticsite/egenius-plone.gif
transmogrify/htmltesting/test_staticsite/file.doc
transmogrify/htmltesting/test_staticsite/file1.htm
transmogrify/htmltesting/test_staticsite/file2.htm
transmogrify/htmltesting/test_staticsite/file3.html
transmogrify/htmltesting/test_staticsite/file4.HTML
transmogrify/htmltesting/test_staticsite/plone_schema.png
transmogrify/htmltesting/test_staticsite/subfolder/subfile1.htm
transmogrify/htmltesting/test_staticsite/subfolder2/subfile1.htm
transmogrify/htmltesting/webstemmer/Makefile
transmogrify/htmltesting/webstemmer/README.txt
transmogrify/htmltesting/webstemmer/__init__.py
transmogrify/htmltesting/webstemmer/analyze.py
transmogrify/htmltesting/webstemmer/extract.py
transmogrify/htmltesting/webstemmer/gzipstream.py
transmogrify/htmltesting/webstemmer/html2txt.py
transmogrify/htmltesting/webstemmer/htmldom.py
transmogrify/htmltesting/webstemmer/htmlparser3.py
transmogrify/htmltesting/webstemmer/htmlutils.py
transmogrify/htmltesting/webstemmer/httplib.py
transmogrify/htmltesting/webstemmer/layoutils.py
transmogrify/htmltesting/webstemmer/perf.py
transmogrify/htmltesting/webstemmer/sgmlparser3.py
transmogrify/htmltesting/webstemmer/style.py
transmogrify/htmltesting/webstemmer/textcrawler.py
transmogrify/htmltesting/webstemmer/urldbutils.py
transmogrify/htmltesting/webstemmer/zipdb.py
transmogrify/htmltesting/webstemmer/docs/compare.png
