Metadata-Version: 1.0
Name: transmogrify.htmltesting
Version: 0.2dev
Summary: utils and transmogrifier blueprints for testing
Home-page: http://www.pretaweb.com
Author: Dylan Jay
Author-email: software@pretaweb.com
License: GPL
Keywords: transmogrifier blueprint funnelweb source plone import conversion microsoft office
Platform: UNKNOWN
Classifier: Programming Language :: Python
Classifier: Topic :: Software Development :: Libraries :: Python Modules
